pylon/__init__.py
pylon/ast_visitor.py
pylon/brute_force_solver.py
pylon/circuit_solver.py
pylon/constraint.py
pylon/ilp_solver.py
pylon/lazy_circuit_solver.py
pylon/lazy_tensor.py
pylon/lazy_torch.py
pylon/sampling_solver.py
pylon/shaped_lazy_solver.py
pylon/solver.py
pylon/tnorm_solver.py
pylon/tree_node.py
pylon/utils.py
pylon_lib-0.1.0.dist-info/LICENSE
pylon_lib-0.1.0.dist-info/METADATA
pylon_lib-0.1.0.dist-info/WHEEL
pylon_lib-0.1.0.dist-info/top_level.txt
pylon_lib-0.1.0.dist-info/RECORD
