Metadata-Version: 2.1
Name: pylon-lib
Version: 0.1.0
Summary: A PyTorch framework for learning with constraints
Home-page: https://pylon-lib.github.io
Author: Kareem Ahmed, Tao Li, Thy Ton, Quan Gio, Kai-Wei Chang, Parisa Kordjamshidi, Vivek Srikumar, Guy Van den Broeck, Sameer Singh
Author-email: ahmedk@cs.ucla.edu
License: Apache 2.0
Project-URL: Pylon source, https://github.com/pylon-lib/pylon
Platform: UNKNOWN
Classifier: License :: OSI Approved :: Apache Software License
Classifier: Programming Language :: Python
Classifier: Programming Language :: Python :: 3
Classifier: Programming Language :: Python :: 3.6
Classifier: Programming Language :: Python :: Implementation :: CPython
Classifier: Programming Language :: Python :: Implementation :: PyPy
Requires-Python: >=3.6.0
License-File: LICENSE
Requires-Dist: astor
Provides-Extra: circuits
Requires-Dist: PySDD ; extra == 'circuits'
